AUTHORS.rst
CONTRIBUTING.rst
HISTORY.rst
LICENSE
MANIFEST.in
README.rst
setup.cfg
setup.py
docs/Makefile
docs/authors.rst
docs/conf.py
docs/contributing.rst
docs/history.rst
docs/index.rst
docs/installation.rst
docs/make.bat
docs/readme.rst
docs/usage.rst
otpstore/__init__.py
otpstore/otpstore.py
otpstore.egg-info/PKG-INFO
otpstore.egg-info/SOURCES.txt
otpstore.egg-info/dependency_links.txt
otpstore.egg-info/not-zip-safe
otpstore.egg-info/requires.txt
otpstore.egg-info/top_level.txt
tests/__init__.py
tests/test_otpstore.py