Metadata-Version: 1.1
Name: otpstore
Version: 0.1.3
Summary: A python package for generating otp keys, storing them in redis and verifying them
Home-page: https://github.com/suryasankar/otpstore
Author: SuryaSankar
Author-email: suryashankar.m@gmail.com
License: MIT license
Keywords: otpstore
Platform: UNKNOWN
Classifier: Development Status :: 2 - Pre-Alpha
Classifier: Intended Audience :: Developers
Classifier: License :: OSI Approved :: MIT License
Classifier: Natural Language :: English
Classifier: Programming Language :: Python :: 3
Classifier: Programming Language :: Python :: 3.5
Classifier: Programming Language :: Python :: 3.6
Classifier: Programming Language :: Python :: 3.7
Classifier: Programming Language :: Python :: 3.8
